{
  "bu-1-0": {
    "cache_creation_input_token_cost": null,
    "cache_read_input_token_cost": 2e-08,
    "input_cost_per_token": 2.0000000000000002e-07,
    "max_input_tokens": null,
    "max_output_tokens": null,
    "max_tokens": null,
    "output_cost_per_token": 2e-06
  },
  "bu-2-0": {
    "cache_creation_input_token_cost": null,
    "cache_read_input_token_cost": 6e-08,
    "input_cost_per_token": 6e-07,
    "max_input_tokens": null,
    "max_output_tokens": null,
    "max_tokens": null,
    "output_cost_per_token": 3.5e-06
  },
  "bu-latest": {
    "cache_creation_input_token_cost": null,
    "cache_read_input_token_cost": 2e-08,
    "input_cost_per_token": 2.0000000000000002e-07,
    "max_input_tokens": null,
    "max_output_tokens": null,
    "max_tokens": null,
    "output_cost_per_token": 2e-06
  },
  "smart": {
    "cache_creation_input_token_cost": null,
    "cache_read_input_token_cost": 2e-08,
    "input_cost_per_token": 2.0000000000000002e-07,
    "max_input_tokens": null,
    "max_output_tokens": null,
    "max_tokens": null,
    "output_cost_per_token": 2e-06
  }
}
